ltvtoolkit/__init__.py
ltvtoolkit/_version.py
ltvtoolkit/core.py
ltvtoolkit-0.1.0.dist-info/licenses/LICENSE.md
ltvtoolkit-0.1.0.dist-info/METADATA
ltvtoolkit-0.1.0.dist-info/WHEEL
ltvtoolkit-0.1.0.dist-info/top_level.txt
ltvtoolkit-0.1.0.dist-info/RECORD
