Metadata-Version: 2.4
Name: ltvtoolkit
Version: 0.1.0
Summary: Customer lifetime value modeling with cohort curves, RFMT, and gradient boosting
Author-email: Your Name <your.email@example.com>
License: MIT
Project-URL: Homepage, https://github.com/yourusername/ltvtoolkit
Project-URL: Repository, https://github.com/yourusername/ltvtoolkit
Project-URL: Issues, https://github.com/yourusername/ltvtoolkit/issues
Keywords: ltv,customer lifetime value,marketing analytics,cohort analysis,predictive modeling
Classifier: Development Status :: 3 - Alpha
Classifier: Intended Audience :: Developers
Classifier: Intended Audience :: Science/Research
Classifier: License :: OSI Approved :: MIT License
Classifier: Programming Language :: Python :: 3
Classifier: Programming Language :: Python :: 3.9
Classifier: Programming Language :: Python :: 3.10
Classifier: Programming Language :: Python :: 3.11
Classifier: Programming Language :: Python :: 3.12
Classifier: Topic :: Scientific/Engineering :: Information Analysis
Classifier: Topic :: Office/Business :: Financial
Requires-Python: >=3.9
License-File: LICENSE.md
Requires-Dist: pandas>=2.0.0
Requires-Dist: numpy>=1.24.0
Requires-Dist: scikit-learn>=1.3.0
Requires-Dist: scipy>=1.10.0
Provides-Extra: full
Requires-Dist: xgboost>=2.0.0; extra == "full"
Requires-Dist: lightgbm>=4.0.0; extra == "full"
Requires-Dist: lifetimes>=0.11.0; extra == "full"
Dynamic: license-file
